TASK3/Src/jtag_tap.v
`timescale 1ns / 1ps
`default_nettype none

module jtag_tap #(
    parameter [31:0] IDCODE_VALUE = 32'h1CAFE003
) (
    input  wire        TCK,
    input  wire        TMS,
    input  wire        TDI,
    output reg         TDO,
    input  wire        TRST_N,

    output wire [3:0]  tap_ir_o,
    output wire        tap_capture_dr_o,
    output wire        tap_shift_dr_o,
    output wire        tap_update_dr_o,

    output reg         debug_halt_req,
    output reg         debug_resume_req,
    output reg         debug_reset_req,

    input  wire        debug_halted,
    input  wire [31:0] debug_pc
);

localparam [3:0]
    TEST_LOGIC_RESET = 4'd0,
    RUN_TEST_IDLE    = 4'd1,
    SELECT_DR_SCAN   = 4'd2,
    CAPTURE_DR       = 4'd3,
    SHIFT_DR         = 4'd4,
    EXIT1_DR         = 4'd5,
    PAUSE_DR         = 4'd6,
    EXIT2_DR         = 4'd7,
    UPDATE_DR        = 4'd8,
    SELECT_IR_SCAN   = 4'd9,
    CAPTURE_IR       = 4'd10,
    SHIFT_IR         = 4'd11,
    EXIT1_IR         = 4'd12,
    PAUSE_IR         = 4'd13,
    EXIT2_IR         = 4'd14,
    UPDATE_IR        = 4'd15;

reg [3:0] tap_state;

function [3:0] next_state;
    input [3:0] current;
    input       tms;
    begin
        case (current)
            TEST_LOGIC_RESET: next_state = tms ? TEST_LOGIC_RESET : RUN_TEST_IDLE;
            RUN_TEST_IDLE:    next_state = tms ? SELECT_DR_SCAN   : RUN_TEST_IDLE;
            SELECT_DR_SCAN:   next_state = tms ? SELECT_IR_SCAN   : CAPTURE_DR;
            CAPTURE_DR:       next_state = tms ? EXIT1_DR         : SHIFT_DR;
            SHIFT_DR:         next_state = tms ? EXIT1_DR         : SHIFT_DR;
            EXIT1_DR:         next_state = tms ? UPDATE_DR        : PAUSE_DR;
            PAUSE_DR:         next_state = tms ? EXIT2_DR         : PAUSE_DR;
            EXIT2_DR:         next_state = tms ? UPDATE_DR        : SHIFT_DR;
            UPDATE_DR:        next_state = tms ? SELECT_DR_SCAN   : RUN_TEST_IDLE;
            SELECT_IR_SCAN:   next_state = tms ? TEST_LOGIC_RESET : CAPTURE_IR;
            CAPTURE_IR:       next_state = tms ? EXIT1_IR         : SHIFT_IR;
            SHIFT_IR:         next_state = tms ? EXIT1_IR         : SHIFT_IR;
            EXIT1_IR:         next_state = tms ? UPDATE_IR        : PAUSE_IR;
            PAUSE_IR:         next_state = tms ? EXIT2_IR         : PAUSE_IR;
            EXIT2_IR:         next_state = tms ? UPDATE_IR        : SHIFT_IR;
            UPDATE_IR:        next_state = tms ? SELECT_DR_SCAN   : RUN_TEST_IDLE;
            default:          next_state = TEST_LOGIC_RESET;
        endcase
    end
endfunction

always @(posedge TCK or negedge TRST_N) begin
    if (!TRST_N)
        tap_state <= TEST_LOGIC_RESET;
    else
        tap_state <= next_state(tap_state, TMS);
end

wire state_capture_dr = (tap_state == CAPTURE_DR);
wire state_shift_dr   = (tap_state == SHIFT_DR);
wire state_update_dr  = (tap_state == UPDATE_DR);
wire state_capture_ir = (tap_state == CAPTURE_IR);
wire state_shift_ir   = (tap_state == SHIFT_IR);
wire state_update_ir  = (tap_state == UPDATE_IR);

assign tap_capture_dr_o = state_capture_dr;
assign tap_shift_dr_o   = state_shift_dr;
assign tap_update_dr_o  = state_update_dr;

localparam [3:0]
    INSTR_IDCODE       = 4'b0001,
    INSTR_DEBUG_CTRL   = 4'b0010,
    INSTR_DEBUG_STATUS = 4'b0011,
    INSTR_DEBUG_PC     = 4'b0100,
    INSTR_BYPASS       = 4'b1111;

reg [3:0] ir_shift;
reg [3:0] ir_reg;

always @(posedge TCK or negedge TRST_N) begin
    if (!TRST_N) begin
        ir_shift <= INSTR_IDCODE;
        ir_reg   <= INSTR_IDCODE;
    end else begin
        if (state_capture_ir)
            ir_shift <= INSTR_IDCODE;
        else if (state_shift_ir)
            ir_shift <= {TDI, ir_shift[3:1]};

        if (state_update_ir) begin
            ir_reg <= ir_shift;
`ifdef BENCH
            $display("IR UPDATE -> %b at time=%0t", ir_shift, $time);
`endif
        end
    end
end

assign tap_ir_o = ir_reg;

// -----------------------------------------------------------------------
// IDCODE register
// -----------------------------------------------------------------------
reg [31:0] idcode_shift;

always @(posedge TCK or negedge TRST_N) begin
    if (!TRST_N)
        idcode_shift <= IDCODE_VALUE;
    else begin
        if (state_capture_dr && (ir_reg == INSTR_IDCODE))
            idcode_shift <= IDCODE_VALUE;
        else if (state_shift_dr && (ir_reg == INSTR_IDCODE))
            idcode_shift <= {TDI, idcode_shift[31:1]};
    end
end

// -----------------------------------------------------------------------
// DEBUG_CTRL register
// -----------------------------------------------------------------------
reg [2:0] dbg_ctrl_shift;
reg [2:0] dbg_ctrl_active;
reg [3:0] dbg_ctrl_hold;

always @(posedge TCK or negedge TRST_N) begin
    if (!TRST_N) begin
        dbg_ctrl_shift   <= 3'b000;
        dbg_ctrl_active  <= 3'b000;
        dbg_ctrl_hold    <= 4'd0;
        debug_halt_req   <= 1'b0;
        debug_resume_req <= 1'b0;
        debug_reset_req  <= 1'b0;
    end else begin
        if (state_capture_dr && (ir_reg == INSTR_DEBUG_CTRL))
            dbg_ctrl_shift <= 3'b000;
        else if (state_shift_dr && (ir_reg == INSTR_DEBUG_CTRL))
            dbg_ctrl_shift <= {dbg_ctrl_shift[1:0], TDI};

        if (state_update_dr && (ir_reg == INSTR_DEBUG_CTRL)) begin
            dbg_ctrl_active <= dbg_ctrl_shift;
            dbg_ctrl_hold   <= 4'd12;
`ifdef BENCH
            $display("JTAG CTRL UPDATE: shift=%b time=%0t", dbg_ctrl_shift, $time);
`endif
        end else if (dbg_ctrl_hold != 4'd0) begin
            dbg_ctrl_hold <= dbg_ctrl_hold - 4'd1;
        end

        debug_halt_req <=
            ((state_update_dr && (ir_reg == INSTR_DEBUG_CTRL) && dbg_ctrl_shift[2]) ||
             ((dbg_ctrl_hold != 4'd0) && dbg_ctrl_active[2]));

        debug_resume_req <=
            ((state_update_dr && (ir_reg == INSTR_DEBUG_CTRL) && dbg_ctrl_shift[1]) ||
             ((dbg_ctrl_hold != 4'd0) && dbg_ctrl_active[1]));

        debug_reset_req <=
            ((state_update_dr && (ir_reg == INSTR_DEBUG_CTRL) && dbg_ctrl_shift[0]) ||
             ((dbg_ctrl_hold != 4'd0) && dbg_ctrl_active[0]));
    end
end

// -----------------------------------------------------------------------
// DEBUG_STATUS register  (FIX 1: added SHIFT_DR advance)
// -----------------------------------------------------------------------
reg dbg_status_shift;

always @(posedge TCK or negedge TRST_N) begin
    if (!TRST_N) begin
        dbg_status_shift <= 1'b0;
    end else begin
        if (state_capture_dr && (ir_reg == INSTR_DEBUG_STATUS)) begin
            dbg_status_shift <= debug_halted;
`ifdef BENCH
            $display("STATUS CAPTURE halted=%b at time=%0t", debug_halted, $time);
`endif
        end else if (state_shift_dr && (ir_reg == INSTR_DEBUG_STATUS)) begin
            // Shift in TDI so the register advances correctly each cycle
            dbg_status_shift <= TDI;
        end
    end
end

// -----------------------------------------------------------------------
// DEBUG_PC register  (FIX 2: shift in TDI instead of 1'b0)
// -----------------------------------------------------------------------
reg [31:0] dbg_pc_shift;

always @(posedge TCK or negedge TRST_N) begin
    if (!TRST_N)
        dbg_pc_shift <= 32'h0;
    else begin
        if (state_capture_dr && (ir_reg == INSTR_DEBUG_PC))
            dbg_pc_shift <= debug_pc;
        else if (state_shift_dr && (ir_reg == INSTR_DEBUG_PC))
            dbg_pc_shift <= {TDI, dbg_pc_shift[31:1]};   // FIX: was {1'b0, ...}
    end
end

`ifdef BENCH
always @(posedge TCK) begin
    if (state_shift_dr && ir_reg == INSTR_DEBUG_PC)
        $display("PC SHIFT tdo=%b shift=%08x time=%0t",
                 dbg_pc_shift[0], dbg_pc_shift, $time);
end
`endif

// -----------------------------------------------------------------------
// BYPASS register
// -----------------------------------------------------------------------
reg bypass_bit;

always @(posedge TCK or negedge TRST_N) begin
    if (!TRST_N)
        bypass_bit <= 1'b0;
    else begin
        if (state_capture_dr && (ir_reg == INSTR_BYPASS))
            bypass_bit <= 1'b0;
        else if (state_shift_dr && (ir_reg == INSTR_BYPASS))
            bypass_bit <= TDI;
    end
end

// -----------------------------------------------------------------------
// TDO multiplexer (combinatorial) — registered on falling TCK edge
// -----------------------------------------------------------------------
reg tdo_mux;

always @(*) begin
    if (state_shift_ir)
        tdo_mux = ir_shift[0];
    else if (state_shift_dr && (ir_reg == INSTR_IDCODE))
        tdo_mux = idcode_shift[0];
    else if (state_shift_dr && (ir_reg == INSTR_DEBUG_CTRL))
        tdo_mux = dbg_ctrl_shift[0];
    else if (state_shift_dr && (ir_reg == INSTR_DEBUG_STATUS))
        tdo_mux = dbg_status_shift;
    else if (state_shift_dr && (ir_reg == INSTR_DEBUG_PC))
        tdo_mux = dbg_pc_shift[0];
    else if (state_shift_dr && (ir_reg == INSTR_BYPASS))
        tdo_mux = bypass_bit;
    else
        tdo_mux = 1'b1;
end

always @(negedge TCK or negedge TRST_N) begin
    if (!TRST_N)
        TDO <= 1'b1;
    else
        TDO <= tdo_mux;
end

`ifdef BENCH
always @(posedge TCK) begin
    if (state_capture_dr && ir_reg == INSTR_DEBUG_PC)
        $display("PC CAPTURE debug_pc=%08x time=%0t", debug_pc, $time);
end

always @(posedge TCK) begin
    if (state_update_dr && ir_reg == INSTR_DEBUG_CTRL)
        $display("CTRL UPDATE shift=%b time=%0t", dbg_ctrl_shift, $time);
end

always @(posedge TCK) begin
    if (state_shift_dr && ir_reg == INSTR_DEBUG_CTRL)
        $display("CTRL SHIFT TDI=%b shift=%b state=%0d time=%0t",
                 TDI, dbg_ctrl_shift, tap_state, $time);
end

always @(posedge TCK) begin
    if (state_shift_ir)
        $display("IR SHIFT TDI=%b ir_shift=%b time=%0t", TDI, ir_shift, $time);
end

always @(negedge TCK) begin
    if (state_shift_dr && ir_reg == INSTR_DEBUG_PC)
        $display("NEGEDGE TDO=%b dbg_pc_shift=%08x", TDO, dbg_pc_shift);
end

always @(posedge TCK) begin
    if (state_update_ir)
        $display("IR UPDATE ir_shift=%b ir_reg=%b", ir_shift, ir_reg);
end
`endif

endmodule

TASK3/Src/tb_top_jtag.v
`timescale 1ns / 1ps
`default_nettype none

module tb_idcode_sim;

    reg  tck = 0, tms = 1, tdi = 0, trst = 0;
    wire tdo;

    jtag_tap #(.IDCODE_VALUE(32'h81262776)) dut (
        .TCK(tck), .TMS(tms), .TDI(tdi), .TDO(tdo), .TRST_N(trst)
    );

    parameter H = 5;

    task tck_cycle;
        begin #H tck=1; #H tck=0; end
    endtask

    task tap_reset;
        integer i;
        begin tms=1; tdi=0; repeat(5) tck_cycle; tms=0; tck_cycle; end
    endtask

    task load_ir;
        input [3:0] instr;
        integer i;
        begin
            tms=1; tck_cycle;       // RTI→SEL_DR
            tms=1; tck_cycle;       // SEL_DR→SEL_IR
            tms=0; tck_cycle;       // SEL_IR→CAP_IR
            tms=0; tck_cycle;       // CAP_IR→SHIFT_IR (entry — no sample)
            for(i=0; i<4; i=i+1) begin
                tdi=instr[i]; tms=(i==3)?1:0; tck_cycle;
            end
            tms=1; tck_cycle;       // EXIT1_IR→UPDATE_IR
            tms=0; tck_cycle;       // UPDATE_IR→RTI
        end
    endtask

    reg [31:0] captured;
    task read_dr32;
        integer i;
        begin
            captured = 0;
            tms=1; tck_cycle;       // RTI→SEL_DR
            tms=0; tck_cycle;       // SEL_DR→CAP_DR  (loads shift reg)
            // Entry: CAP_DR→SHIFT_DR. Sample TDO on this negedge = bit[0]
            tms=0;
            #H tck=1; #H tck=0; #1 captured[0] = tdo;
            // 31 remaining bits
            for(i=1; i<32; i=i+1) begin
                tdi=0; tms=(i==31)?1:0;
                #H tck=1; #H tck=0; #1 captured[i] = tdo;
            end
            tms=1; tck_cycle;       // EXIT1_DR→UPDATE_DR
            tms=0; tck_cycle;       // UPDATE_DR→RTI
        end
    endtask

    initial begin
        $dumpfile("tb_idcode_sim.vcd");
        $dumpvars(0, tb_idcode_sim);
        #20 trst = 1;
        tap_reset;

        load_ir(4'b0001);   // IDCODE
        read_dr32;
        $display("IDCODE = 0x%08x (expected 0x81262776)", captured);

        if (captured === 32'h81262776)
            $display("TASK 3A SIM PASSED");
        else
            $display("FAIL: got 0x%08x", captured);

        $finish;
    end

endmodule

TASK3/src/tb_idcode_sim.vcd
$date
	Thu Jun 11 12:47:16 2026
$end
$version
	Icarus Verilog
$end
$timescale
	1ps
$end
$scope module tb_idcode_sim $end
$var wire 1 ! tdo $end
$var reg 32 " captured [31:0] $end
$var reg 1 # tck $end
$var reg 1 $ tdi $end
$var reg 1 % tms $end
$var reg 1 & trst $end
$scope module dut $end
$var wire 1 # TCK $end
$var wire 1 $ TDI $end
$var wire 1 % TMS $end
$var wire 1 & TRST_N $end
$var wire 1 ' debug_halted $end
$var wire 32 ( debug_pc [31:0] $end
$var wire 1 ) tap_capture_dr_o $end
$var wire 4 * tap_ir_o [3:0] $end
$var wire 1 + tap_shift_dr_o $end
$var wire 1 , tap_update_dr_o $end
$var wire 1 - state_update_ir $end
$var wire 1 . state_update_dr $end
$var wire 1 / state_shift_ir $end
$var wire 1 0 state_shift_dr $end
$var wire 1 1 state_capture_ir $end
$var wire 1 2 state_capture_dr $end
$var reg 1 ! TDO $end
$var reg 1 3 bypass_bit $end
$var reg 3 4 dbg_ctrl_active [2:0] $end
$var reg 4 5 dbg_ctrl_hold [3:0] $end
$var reg 3 6 dbg_ctrl_shift [2:0] $end
$var reg 32 7 dbg_pc_shift [31:0] $end
$var reg 1 8 dbg_status_shift $end
$var reg 1 9 debug_halt_req $end
$var reg 1 : debug_reset_req $end
$var reg 1 ; debug_resume_req $end
$var reg 32 < idcode_shift [31:0] $end
$var reg 4 = ir_reg [3:0] $end
$var reg 4 > ir_shift [3:0] $end
$var reg 4 ? tap_state [3:0] $end
$var reg 1 @ tdo_mux $end
$scope function next_state $end
$var reg 4 A current [3:0] $end
$var reg 1 B tms $end
$upscope $end
$upscope $end
$scope task load_ir $end
$var reg 4 C instr [3:0] $end
$var integer 32 D i [31:0] $end
$upscope $end
$scope task read_dr32 $end
$var integer 32 E i [31:0] $end
$upscope $end
$scope task tap_reset $end
$upscope $end
$scope task tck_cycle $end
$upscope $end
$upscope $end
$enddefinitions $end
#0
$dumpvars
bx E
bx D
bx C
xB
bx A
x@
bx ?
bx >
bx =
bx <
x;
x:
x9
x8
bx 7
bx 6
bx 5
bx 4
x3
x2
x1
x0
x/
x.
x-
x,
x+
bx *
x)
bz (
z'
0&
1%
0$
0#
bx "
x!
$end
#20000
1&
#25000
1@
0)
02
0+
00
0,
0.
01
0/
0-
b0 ?
1B
1#
#30000
1!
0#
#35000
b0 A
1#
#40000
0#
#45000
1#
#50000
0#
#55000
1#
#60000
0#
#65000
1#
#70000
0%
0#
#75000
b1 ?
0B
1#
#80000
1%
b1 C
0#
#85000
b10 ?
b1 A
1B
1#
#90000
0#
#95000
b1001 ?
b10 A
1#
#100000
0%
0#
#105000
11
b1010 ?
b1001 A
0B
1#
#110000
0#
#115000
b1 >
01
1/
b1011 ?
b1010 A
1#
#120000
1$
b0 D
0#
#125000
0@
b1000 >
b1011 A
1#
#130000
0!
0$
b1 D
0#
#135000
b100 >
1#
#140000
b10 D
0#
#145000
b10 >
1#
#150000
1%
b11 D
0#
#155000
1@
b1 >
0/
b1100 ?
1B
1#
#160000
1!
b100 D
0#
#165000
1-
b1111 ?
b1100 A
1#
#170000
0%
0#
#175000
b1 *
b1 =
0-
b1 ?
b1111 A
0B
1#
#180000
1%
b0 "
0#
#185000
b10 ?
b1 A
1B
1#
#190000
0%
0#
#195000
1)
12
b11 ?
b10 A
0B
1#
#200000
0#
#205000
0@
0)
02
1+
10
b100 ?
b10000001001001100010011101110110 <
b11 A
1#
#210000
0!
0#
#211000
b1 E
#216000
1@
b1000000100100110001001110111011 <
b100 A
1#
#221000
1!
0#
#222000
b10 E
b10 "
#227000
b100000010010011000100111011101 <
1#
#232000
0#
#233000
b11 E
b110 "
#238000
0@
b10000001001001100010011101110 <
1#
#243000
0!
0#
#244000
b100 E
#249000
1@
b1000000100100110001001110111 <
1#
#254000
1!
0#
#255000
b101 E
b10110 "
#260000
b100000010010011000100111011 <
1#
#265000
0#
#266000
b110 E
b110110 "
#271000
b10000001001001100010011101 <
1#
#276000
0#
#277000
b111 E
b1110110 "
#282000
0@
b1000000100100110001001110 <
1#
#287000
0!
0#
#288000
b1000 E
#293000
1@
b100000010010011000100111 <
1#
#298000
1!
0#
#299000
b1001 E
b101110110 "
#304000
b10000001001001100010011 <
1#
#309000
0#
#310000
b1010 E
b1101110110 "
#315000
b1000000100100110001001 <
1#
#320000
0#
#321000
b1011 E
b11101110110 "
#326000
0@
b100000010010011000100 <
1#
#331000
0!
0#
#332000
b1100 E
#337000
b10000001001001100010 <
1#
#342000
0#
#343000
b1101 E
#348000
1@
b1000000100100110001 <
1#
#353000
1!
0#
#354000
b1110 E
b10011101110110 "
#359000
0@
b100000010010011000 <
1#
#364000
0!
0#
#365000
b1111 E
#370000
b10000001001001100 <
1#
#375000
0#
#376000
b10000 E
#381000
b1000000100100110 <
1#
#386000
0#
#387000
b10001 E
#392000
1@
b100000010010011 <
1#
#397000
1!
0#
#398000
b10010 E
b100010011101110110 "
#403000
b10000001001001 <
1#
#408000
0#
#409000
b10011 E
b1100010011101110110 "
#414000
0@
b1000000100100 <
1#
#419000
0!
0#
#420000
b10100 E
#425000
b100000010010 <
1#
#430000
0#
#431000
b10101 E
#436000
1@
b10000001001 <
1#
#441000
1!
0#
#442000
b10110 E
b1001100010011101110110 "
#447000
0@
b1000000100 <
1#
#452000
0!
0#
#453000
b10111 E
#458000
b100000010 <
1#
#463000
0#
#464000
b11000 E
#469000
1@
b10000001 <
1#
#474000
1!
0#
#475000
b11001 E
b1001001100010011101110110 "
#480000
0@
b1000000 <
1#
#485000
0!
0#
#486000
b11010 E
#491000
b100000 <
1#
#496000
0#
#497000
b11011 E
#502000
b10000 <
1#
#507000
0#
#508000
b11100 E
#513000
b1000 <
1#
#518000
0#
#519000
b11101 E
#524000
b100 <
1#
#529000
0#
#530000
b11110 E
#535000
b10 <
1#
#540000
0#
#541000
1%
b11111 E
#546000
1@
b1 <
0+
00
b101 ?
1B
1#
#551000
1!
0#
#552000
b100000 E
b10000001001001100010011101110110 "
#557000
1,
1.
b1000 ?
b101 A
1#
#562000
0%
0#
#567000
0,
0.
b1 ?
b1000 A
0B
1#
#572000
0#
